recurring_ical_events/.gitignore
recurring_ical_events/__init__.py
recurring_ical_events/_version.py
recurring_ical_events/constants.py
recurring_ical_events/errors.py
recurring_ical_events/examples.py
recurring_ical_events/occurrence.py
recurring_ical_events/pages.py
recurring_ical_events/query.py
recurring_ical_events/types.py
recurring_ical_events/util.py
recurring_ical_events/version.py
recurring_ical_events/adapters/__init__.py
recurring_ical_events/adapters/alarm.py
recurring_ical_events/adapters/component.py
recurring_ical_events/adapters/event.py
recurring_ical_events/adapters/journal.py
recurring_ical_events/adapters/todo.py
recurring_ical_events/selection/__init__.py
recurring_ical_events/selection/alarm.py
recurring_ical_events/selection/all.py
recurring_ical_events/selection/base.py
recurring_ical_events/selection/name.py
recurring_ical_events/series/__init__.py
recurring_ical_events/series/alarm.py
recurring_ical_events/series/rrule.py
recurring_ical_events/test/__init__.py
recurring_ical_events/test/conftest.py
recurring_ical_events/test/py.py
recurring_ical_events/test/test_after.py
recurring_ical_events/test/test_at_function.py
recurring_ical_events/test/test_bad_rrule_format.py
recurring_ical_events/test/test_convert_inputs.py
recurring_ical_events/test/test_count.py
recurring_ical_events/test/test_daylight_saving_time.py
recurring_ical_events/test/test_deleted_entries.py
recurring_ical_events/test/test_duration.py
recurring_ical_events/test/test_end_before_start_event.py
recurring_ical_events/test/test_event_values_and_edits.py
recurring_ical_events/test/test_example_function.py
recurring_ical_events/test/test_examples.py
recurring_ical_events/test/test_extend_classes.py
recurring_ical_events/test/test_issue_101_select_components.py
recurring_ical_events/test/test_issue_107_omitting_last_event.py
recurring_ical_events/test/test_issue_113_period_in_rdate.py
recurring_ical_events/test/test_issue_117_until_before_dtstart.py
recurring_ical_events-3.7.1.dist-info/METADATA
recurring_ical_events-3.7.1.dist-info/WHEEL
recurring_ical_events-3.7.1.dist-info/licenses/LICENSE
recurring_ical_events-3.7.1.dist-info/RECORD
