Metadata-Version: 2.4
Name: recurring-ical-events
Version: 3.7.1
Summary: Calculate recurrence times of events, todos, alarms and journals based on icalendar RFC5545.
Project-URL: Homepage, https://recurring-ical-events.readthedocs.io/
Project-URL: Repository, https://github.com/niccokunzmann/python-recurring-ical-events
Project-URL: Source Archive, https://github.com/niccokunzmann/python-recurring-ical-events/archive/7057e709e36eea505d05639f16f2659c616bd9cd.zip
Project-URL: Issues, https://github.com/niccokunzmann/python-recurring-ical-events/issues
Project-URL: Documentation, https://github.com/niccokunzmann/python-recurring-ical-events
Project-URL: Changelog, https://github.com/niccokunzmann/python-recurring-ical-events?tab=readme-ov-file#changelog
Project-URL: Fund with GitHub Sponsors, https://github.com/sponsors/niccokunzmann
Project-URL: Fund with Polar, https://polar.sh/niccokunzmann/python-recurring-ical-events
Project-URL: Fund with Open Collective, https://opencollective.com/open-web-calendar
Project-URL: Fund with Tidelift, https://tidelift.com/funding/github/pypi/recurring-ical-events
Author-email: Nicco Kunzmann <niccokunzmann@rambler.ru>
Maintainer-email: Nicco Kunzmann <niccokunzmann@rambler.ru>
License-Expression: GPL-3.0-or-later
License-File: LICENSE
Keywords: alarm,calendar,events,icalendar,ics,journal,rfc5545,scheduling,todo
Classifier: Development Status :: 5 - Production/Stable
Classifier: Intended Audience :: Developers
Classifier: Natural Language :: English
Classifier: Operating System :: OS Independent
Classifier: Programming Language :: Python :: 3
Classifier: Programming Language :: Python :: 3 :: Only
Classifier: Programming Language :: Python :: 3.8
Classifier: Programming Language :: Python :: 3.9
Classifier: Programming Language :: Python :: 3.10
Classifier: Programming Language :: Python :: 3.11
Classifier: Programming Language :: Python :: 3.12
Classifier: Programming Language :: Python :: 3.13
Classifier: Topic :: Office/Business :: Scheduling
Classifier: Topic :: Software Development :: Libraries :: Python Modules
Classifier: Topic :: Utilities
Requires-Python: >=3.8
Requires-Dist: backports-zoneinfo; python_version == '3.7' or python_version == '3.8'
Requires-Dist: icalendar<7.0.0,>=6.1.0
Requires-Dist: python-dateutil<3.0.0,>=2.8.1
Requires-Dist: typing-extensions; python_version <= '3.9'
Requires-Dist: tzdata
Requires-Dist: x-wr-timezone<3.0.0,>=1.0.0; python_version >= '3.9'
Requires-Dist: x-wr-timezone==0.*; python_version <= '3.8'
Provides-Extra: test
Requires-Dist: pygments; extra == 'test'
Requires-Dist: pytest; extra == 'test'
Requires-Dist: pytest-cov; extra == 'test'
Requires-Dist: pytz>=2023.3; extra == 'test'
Requires-Dist: restructuredtext-lint; extra == 'test'
